personalDatabase/__init__.py
personalDatabase/foundation.py
personalDatabase/test.py
personalDatabase/utility.py
personalDatabase/references/__init__.py
personalDatabase/references/actions.py
personalDatabase/references/function_usage.py
personalDatabase/references/remote_connection.py
personalDatabase-2.4.0.dist-info/METADATA
personalDatabase-2.4.0.dist-info/WHEEL
personalDatabase-2.4.0.dist-info/entry_points.txt
personalDatabase-2.4.0.dist-info/top_level.txt
personalDatabase-2.4.0.dist-info/RECORD
